{
    "id": "45043855",
    "公司狀況": "解散",
    "公司名稱": "傑科科技股份有限公司",
    "資本總額(元)": "15,000,000",
    "實收資本額(元)": "15,000,000",
    "代表人姓名": "",
    "公司所在地": "桃園市平鎮區湧豐里工業二路七之一號",
    "登記機關": "經濟部中部辦公室",
    "核准設立日期": {
        "year": 1980,
        "month": 5,
        "day": 10
    },
    "最後核准變更日期": {
        "year": 2005,
        "month": 3,
        "day": 28
    },
    "所營事業資料": [
        [
            "",
            "１﹒各種機械及其零件製造加工修理組立及買賣。"
        ],
        [
            "",
            "２﹒棉布纖維布之織造加工買賣。"
        ],
        [
            "",
            "３﹒前各項有關產品及其原料之進出口貿易業務。"
        ],
        [
            "ZZ99999",
            "除許可業務外，得經營法令非禁止或限制之業務"
        ]
    ],
    "董監事名單": [
        {
            "序號": "0004",
            "職稱": "監察人",
            "姓名": "周_純",
            "所代表法人": "",
            "出資額": "0"
        }
    ],
    "經理人名單": [],
    "舊營業項目資料": "http:\/\/gcis.nat.gov.tw..\/cmpy\/cmpyOriginalBusiItemAction.do?method=detail&banNo=45043855",
    "公司狀況日期": {
        "year": 2005,
        "month": 6,
        "day": 22
    },
    "公司狀況文號": "經授中字 第0943232997號"
}