{
    "id": "97222627",
    "公司狀況": "核准設立",
    "公司名稱": "艾弗特實業有限公司",
    "資本總額(元)": "5,000,000",
    "代表人姓名": "張_烱",
    "公司所在地": "基隆市仁愛區仁三路一一號九樓之三",
    "登記機關": "經濟部中部辦公室",
    "核准設立日期": {
        "year": 1996,
        "month": 9,
        "day": 20
    },
    "最後核准變更日期": {
        "year": 2005,
        "month": 10,
        "day": 27
    },
    "所營事業資料": [
        [
            "",
            "１﹒一般進出口貿易業務。（許可業務除外）"
        ],
        [
            "",
            "２﹒建築五金材料買賣及進出口業務。"
        ],
        [
            "",
            "３﹒橡塑膠原料買賣、進出口業務。"
        ],
        [
            "",
            "４﹒皮包、皮鞋、皮飾、皮衣買賣及進出口業務。"
        ]
    ],
    "董監事名單": [
        {
            "序號": "0001",
            "職稱": "董事",
            "姓名": "張_烱",
            "所代表法人": "",
            "出資額": "1,000,000"
        }
    ],
    "經理人名單": [],
    "停業日期(起)": {
        "year": 2012,
        "month": 10,
        "day": 23
    },
    "停業日期(迄)": {
        "year": 2013,
        "month": 10,
        "day": 22
    }
}