{
    "id": "97360634",
    "公司狀況": "解散",
    "公司名稱": "義薪企業有限公司",
    "資本總額(元)": "10,000,000",
    "代表人姓名": "",
    "公司所在地": "高雄市林園區忠義二街71號1樓",
    "登記機關": "高雄市政府經濟發展局",
    "核准設立日期": {
        "year": 1997,
        "month": 1,
        "day": 15
    },
    "最後核准變更日期": {
        "year": 2006,
        "month": 4,
        "day": 26
    },
    "所營事業資料": [
        [
            "",
            "１﹒輸送機械、石化機械、機械零件、塑膠袋之買賣內外銷業務。"
        ],
        [
            "",
            "２﹒五金、塑膠管買賣內外銷業務。"
        ],
        [
            "",
            "３﹒鋁殼、油槽、配管（自來水管及燃料導管除外）冷熱作工程及機械、油漆、酸洗"
        ],
        [
            "",
            "　、保溫（冷凍空調業除外）強化塑膠、耐酸工程設計按裝承包。"
        ],
        [
            "",
            "４﹒金屬品（機械零件）焚化爐、鍋爐、塔槽、鋼鐵塔、熱交換器、防塵設備、防塵"
        ],
        [
            "",
            "　機械設計按裝。"
        ],
        [
            "",
            "５﹒轉動機械、瀝青機械、化學機械、吊車機械、昇降機械、污水機械設備、加熱爐"
        ],
        [
            "",
            "　、鋼鐵管、柏油包覆、起重（特許業務外）及各種防腐工程設計按裝。"
        ],
        [
            "",
            "６﹒代理前各項國內外廠商產品投標報價銷售業務。"
        ]
    ],
    "董監事名單": [],
    "經理人名單": [],
    "停業日期(起)": {
        "year": 2010,
        "month": 5,
        "day": 5
    },
    "停業日期(迄)": {
        "year": 2011,
        "month": 5,
        "day": 4
    },
    "舊營業項目資料": "http:\/\/gcis.nat.gov.tw..\/cmpy\/cmpyOriginalBusiItemAction.do?method=detail&banNo=97360634",
    "公司狀況日期": {
        "year": 2011,
        "month": 4,
        "day": 28
    },
    "公司狀況文號": "高市府四維經商公字 第1000116588號"
}