{
    "id": "97397034",
    "公司狀況": "廢止",
    "公司名稱": "樺達廣告有限公司",
    "資本總額(元)": "500,000",
    "代表人姓名": "",
    "公司所在地": "臺中市南屯區大墩路八八二號三樓",
    "登記機關": "臺中市政府",
    "核准設立日期": {
        "year": 1997,
        "month": 3,
        "day": 12
    },
    "最後核准變更日期": {
        "year": 2002,
        "month": 10,
        "day": 31
    },
    "所營事業資料": [
        [
            "I401010",
            "一般廣告服務業。"
        ],
        [
            "I503010",
            "景觀、室內設計業。（建築師業務除外）（建築室內裝修業除外）"
        ],
        [
            "E801010",
            "室內裝潢業（營造業除外）（建築室內裝修業除外）。"
        ],
        [
            "F211010",
            "建材零售業。"
        ],
        [
            "F401010",
            "國際貿易業。"
        ]
    ],
    "董監事名單": [],
    "經理人名單": [],
    "舊營業項目資料": "http:\/\/gcis.nat.gov.tw..\/cmpy\/cmpyOriginalBusiItemAction.do?method=detail&banNo=97397034",
    "公司狀況日期": {
        "year": 2008,
        "month": 3,
        "day": 14
    },
    "公司狀況文號": "經授中字 第0973473570號"
}