{
    "id": "75469694",
    "公司狀況": "核准設立",
    "公司名稱": "健行企業有限公司",
    "資本總額(元)": "2,000,000",
    "代表人姓名": "許_惠",
    "公司所在地": "高雄市左營區新下街178號1樓",
    "登記機關": "高雄市政府經濟發展局",
    "核准設立日期": {
        "year": 1968,
        "month": 8,
        "day": 9
    },
    "最後核准變更日期": {
        "year": 2022,
        "month": 3,
        "day": 17
    },
    "所營事業資料": [
        [
            "",
            "一蒸餾水及附屬用品製造及買賣代銷業．"
        ],
        [
            "",
            "二食品、五金、什貨買賣代銷業．"
        ],
        [
            "",
            "三冰塊製造及買賣代銷業．"
        ],
        [
            "",
            "四水泥加工製品之買賣︹電焊基椿鐵路用ＰＣ枕標椿管類、瓦類、圍墻等︺．"
        ],
        [
            "",
            "五鋁窗、鋁門設計按裝業務．"
        ],
        [
            "",
            "六五金器材買賣業務．"
        ],
        [
            "",
            "七衛生器材、鋼鐵器具、被服買賣出口等業務．"
        ],
        [
            "",
            "八礦產品及砂石採購出口業務．"
        ],
        [
            "",
            "九蒸汽鍋爐及燃料油系統之設計按裝．"
        ]
    ],
    "董監事名單": [
        {
            "序號": "0001",
            "職稱": "董事",
            "姓名": "許_惠",
            "所代表法人": "",
            "出資額": "2,000,000"
        }
    ],
    "經理人名單": [],
    "章程所訂外文公司名稱": ""
}