{
    "id": "75956596",
    "公司狀況": "核准設立",
    "公司名稱": "蘭宜企業有限公司",
    "資本總額(元)": "1,000,000",
    "代表人姓名": "",
    "公司所在地": "高雄市新興區八德一路229號",
    "登記機關": "高雄市政府經濟發展局",
    "核准設立日期": {
        "year": 1978,
        "month": 9,
        "day": 1
    },
    "最後核准變更日期": null,
    "所營事業資料": [
        [
            "",
            "１﹒重機及汽車零件船舶機件電工器材及有關五金買賣及進出口貿易業"
        ],
        [
            "",
            "務"
        ],
        [
            "",
            "２﹒前項有關進出口貿易業務得為與有關同業間對外保證"
        ],
        [
            "",
            "３﹒汽車零件船舶引擎、機件電器機件等製造"
        ],
        [
            "",
            "４﹒上項有關事業之經營及投資"
        ]
    ],
    "董監事名單": [],
    "經理人名單": []
}