{
    "id": "76405375",
    "公司狀況": "核准設立",
    "公司名稱": "承品企業有限公司",
    "資本總額(元)": "1,000,000",
    "代表人姓名": "方_印",
    "公司所在地": "高雄市岡山區育才路７２巷６號",
    "登記機關": "高雄市政府經濟發展局",
    "核准設立日期": {
        "year": 1983,
        "month": 2,
        "day": 23
    },
    "最後核准變更日期": {
        "year": 2012,
        "month": 2,
        "day": 17
    },
    "所營事業資料": [
        [
            "",
            "一各種電氣機械器具︹各種打入式地鈕、拉線地鈕等︺機械器具、電子五金零件、"
        ],
        [
            "",
            "接地棒、各種機械及其五金零配件之製造加工買賣業務．"
        ],
        [
            "",
            "二鐵座、銑座、基礎螺絲、燈具、燈柱製造加工買賣業務．"
        ],
        [
            "",
            "三有關之進出口貿易業務．"
        ],
        [
            "",
            "四代理國內外廠商有關產品之投標報價及經銷業務︹期貨除外︺．"
        ]
    ],
    "董監事名單": [
        {
            "序號": "0001",
            "職稱": "董事",
            "姓名": "方_印",
            "所代表法人": "",
            "出資額": "200,000"
        }
    ],
    "經理人名單": []
}