{
    "id": "30880354",
    "公司狀況": "核准設立",
    "公司名稱": "協錦水電工程有限公司",
    "資本總額(元)": "1,000,000",
    "代表人姓名": "蔡_廣",
    "公司所在地": "臺北市中正區新生南路1段126之6號5樓",
    "登記機關": "臺北市政府",
    "核准設立日期": {
        "year": 1986,
        "month": 1,
        "day": 1
    },
    "最後核准變更日期": null,
    "所營事業資料": [
        [
            "",
            "１﹒各種高低壓電氣工程之設計及承攬業務。"
        ],
        [
            "",
            "２﹒空調冷氣設備工程之設計及承攬業務。"
        ],
        [
            "",
            "３﹒各種內外線給水衛生工程之設計及承攬業務。"
        ],
        [
            "",
            "４﹒有關前各項工程器材之買賣及進出口貿易業務與其同業間之對外保證。"
        ],
        [
            "",
            "５﹒前各項有關業務之經營及投資。"
        ]
    ],
    "董監事名單": [
        {
            "序號": "0001",
            "職稱": "執行業務股東",
            "姓名": "蔡_廣",
            "所代表法人": "",
            "出資額": "900,000"
        }
    ],
    "經理人名單": []
}