{
    "id": "34386926",
    "公司狀況": "解散",
    "公司名稱": "？玲實業有限公司",
    "資本總額(元)": "10,000,000",
    "代表人姓名": "",
    "公司所在地": "雲林縣麥寮鄉麥豐村十鄰自強路六十五號一樓",
    "登記機關": "經濟部中部辦公室",
    "核准設立日期": {
        "year": 1982,
        "month": 5,
        "day": 27
    },
    "最後核准變更日期": {
        "year": 2000,
        "month": 7,
        "day": 12
    },
    "所營事業資料": [
        [
            "",
            "１﹒建材（空心門門窗）木材五金（門鎖）家具（衣櫃）之加工製造及買賣。"
        ],
        [
            "",
            "２﹒室內裝潢設計及承包施工。"
        ],
        [
            "",
            "３﹒油漆工程施工。"
        ],
        [
            "",
            "４﹒有關進出口業務及同業間對外保證。"
        ],
        [
            "",
            "５﹒有關國內外之代理投標報價承包業務。"
        ],
        [
            "",
            "６﹒有關業務之經營及投資。"
        ]
    ],
    "董監事名單": [],
    "經理人名單": [],
    "舊營業項目資料": "http:\/\/gcis.nat.gov.tw..\/cmpy\/cmpyOriginalBusiItemAction.do?method=detail&banNo=34386926",
    "公司狀況日期": {
        "year": 2000,
        "month": 7,
        "day": 12
    },
    "公司狀況文號": "經89中字 第089459984號"
}