{
    "id": "69664066",
    "公司狀況": "解散",
    "公司名稱": "應和企業股份有限公司",
    "資本總額(元)": "5,000,000",
    "實收資本額(元)": "5,000,000",
    "代表人姓名": "",
    "公司所在地": "臺南市北區北園街104號  ",
    "登記機關": "臺南市政府",
    "核准設立日期": {
        "year": 1981,
        "month": 3,
        "day": 16
    },
    "最後核准變更日期": {
        "year": 2007,
        "month": 3,
        "day": 8
    },
    "所營事業資料": [
        [
            "",
            "１﹒各種染料、顏料、化學藥料及有關染色用之助劑製造加工買賣（特許業務除外）"
        ],
        [
            "",
            "２﹒咖啡豆（不設座）食品（牛奶茶葉類）買賣業務。"
        ],
        [
            "",
            "３﹒塑膠粒、塑膠原料、塑膠添加劑、抗靜電劑、無機塩類、石化中間原料、濃縮色"
        ],
        [
            "",
            "　料、鐘錶計算機、鞋類（皮鞋布鞋、塑膠鞋）文具用品（鋼筆、原子筆）眼鏡（"
        ],
        [
            "",
            "　塑膠、金屬鏡框）裝飾品（髮夾、項鍊、耳環、手鐲、戒指　）化粧品）口紅、"
        ],
        [
            "",
            "　眼影、粉餅、香水）體育用品（網球拍、球類）進出口買賣。（銀樓業除外）"
        ],
        [
            "",
            "４﹒汽車塑膠零件、塑膠飾品、電子零件、玻璃纖維、動物纖維、合成纖維進出口買"
        ],
        [
            "",
            "　賣業務。"
        ],
        [
            "",
            "５﹒前項有關國內外廠之代理業務（期貨除外）並就進出口業務得為同業間對外保證"
        ],
        [
            "",
            "　。"
        ],
        [
            "",
            "６﹒前各項有關業務之經營及投資。"
        ]
    ],
    "董監事名單": [
        {
            "序號": "0005",
            "職稱": "監察人",
            "姓名": "郭_和",
            "所代表法人": "",
            "出資額": "1,500"
        }
    ],
    "經理人名單": [
        {
            "序號": "0006",
            "姓名": "莊_秀",
            "到職日期": {
                "year": 1981,
                "month": 1,
                "day": 7
            }
        }
    ],
    "停業日期(起)": {
        "year": 2018,
        "month": 3,
        "day": 25
    },
    "停業日期(迄)": {
        "year": 2019,
        "month": 3,
        "day": 24
    },
    "舊營業項目資料": "https:\/\/gcis.nat.gov.tw..\/cmpy\/cmpyOriginalBusiItemAction.do?method=detail&banNo=69664066",
    "停業核准(備)機關": "財政部南區國稅局臺南分局",
    "公司狀況日期": {
        "year": 2018,
        "month": 12,
        "day": 26
    },
    "公司狀況文號": "府經工商字 第1071135351號"
}