{
    "id": "16591494",
    "公司狀況": "解散",
    "公司名稱": "豐穎投資股份有限公司",
    "資本總額(元)": "198,000,000",
    "實收資本額(元)": "198,000,000",
    "代表人姓名": "",
    "公司所在地": "臺北市中山區長安東路二段九十九號八樓",
    "登記機關": "經濟部商業司",
    "核准設立日期": {
        "year": 1998,
        "month": 6,
        "day": 1
    },
    "最後核准變更日期": {
        "year": 2001,
        "month": 1,
        "day": 29
    },
    "所營事業資料": [
        [
            "H201010",
            "一般投資業"
        ]
    ],
    "董監事名單": [
        {
            "序號": "0004",
            "職稱": "監察人",
            "姓名": "台_設",
            "所代表法人": "",
            "出資額": "360,000"
        }
    ],
    "經理人名單": [],
    "舊營業項目資料": "http:\/\/gcis.nat.gov.tw..\/cmpy\/cmpyOriginalBusiItemAction.do?method=detail&banNo=16591494",
    "公司狀況日期": {
        "year": 2001,
        "month": 1,
        "day": 29
    },
    "公司狀況文號": "經商字 第09001021370號"
}