{
    "id": "16817752",
    "公司狀況": "核准設立",
    "公司名稱": "南洲工程有限公司",
    "資本總額(元)": "5,000,000",
    "代表人姓名": "何_龍",
    "公司所在地": "高雄市小港區宏平路582之1號1樓",
    "登記機關": "高雄市政府經濟發展局",
    "核准設立日期": {
        "year": 1999,
        "month": 11,
        "day": 8
    },
    "最後核准變更日期": {
        "year": 2011,
        "month": 3,
        "day": 31
    },
    "所營事業資料": [
        [
            "",
            "一Ｊ１０１０３０廢棄物清除業．"
        ],
        [
            "",
            "二Ｊ１０１０４０廢棄物處理業．"
        ],
        [
            "",
            "三ＥＺ０２０１０起重工程業．"
        ],
        [
            "",
            "四Ｆ１１３０１０機械批發業．"
        ],
        [
            "",
            "五Ｆ１０６０１０五金批發業．"
        ],
        [
            "",
            "六Ｅ５９９０１０配管工程業．"
        ],
        [
            "",
            "七Ｆ１１３０３０精密儀器批發業．（度量衡器除外）"
        ],
        [
            "",
            "八Ｆ１１３０５０事務性機器設備批發業．"
        ],
        [
            "",
            "九Ｉ６０１０１０租賃業．"
        ],
        [
            "",
            "十Ｆ４０１０１０國際貿易業．"
        ],
        [
            "",
            "十一Ｅ２０１０１０景觀工程業．"
        ]
    ],
    "董監事名單": [
        {
            "序號": "0001",
            "職稱": "董事",
            "姓名": "何_龍",
            "所代表法人": "",
            "出資額": "675,000"
        }
    ],
    "經理人名單": []
}