{
    "id": "00715771",
    "公司狀況": "核准設立",
    "公司名稱": "代眾車業有限公司",
    "資本總額(元)": "1,000,000",
    "代表人姓名": "黃_珠",
    "公司所在地": "基隆市七堵區實踐路290號1樓",
    "登記機關": "經濟部中部辦公室",
    "核准設立日期": {
        "year": 1981,
        "month": 6,
        "day": 17
    },
    "最後核准變更日期": {
        "year": 2011,
        "month": 4,
        "day": 6
    },
    "所營事業資料": [
        [
            "",
            "１﹒車輛及其零件材料買賣。"
        ],
        [
            "",
            "２﹒有關車輛保養檢修業務。"
        ],
        [
            "",
            "３﹒上項有關產品之代辦銷購業務。"
        ],
        [
            "",
            "４﹒代客申辦車輛檢驗業務。"
        ]
    ],
    "董監事名單": [
        {
            "序號": "0001",
            "職稱": "董事長",
            "姓名": "黃_珠",
            "所代表法人": "",
            "出資額": "300,000"
        },
        {
            "序號": "0002",
            "職稱": "董事",
            "姓名": "陸_雅",
            "所代表法人": "",
            "出資額": "200,000"
        },
        {
            "序號": "0003",
            "職稱": "董事",
            "姓名": "黃_評",
            "所代表法人": "",
            "出資額": "100,000"
        }
    ],
    "經理人名單": []
}