{
    "id": "04269366",
    "公司狀況": "撤銷",
    "公司名稱": "亞美金屬工業有限公司",
    "資本總額(元)": "1,000,000",
    "代表人姓名": "",
    "公司所在地": "新竹縣湖口鄉鳳凰村２２鄰光復南路１４號",
    "登記機關": "經濟部中部辦公室",
    "核准設立日期": {
        "year": 1976,
        "month": 4,
        "day": 6
    },
    "最後核准變更日期": {
        "year": 1989,
        "month": 2,
        "day": 20
    },
    "所營事業資料": [
        [
            "",
            "１﹒鋁門窗、鋁梯、鋁製品裝配及買賣"
        ],
        [
            "",
            "２﹒有關鋁料、鋁條、鋁擠型之買賣業務"
        ],
        [
            "",
            "３﹒金屬、銅管、銅棒、銅條、銅片之製造及買賣與內外銷業務"
        ],
        [
            "",
            "４﹒前項事業有關之投資及經營"
        ]
    ],
    "董監事名單": [],
    "經理人名單": []
}