{
    "id": "07692393",
    "公司狀況": "核准設立",
    "公司名稱": "欣慶投資開發股份有限公司",
    "資本總額(元)": "76,000,000",
    "實收資本額(元)": "76,000,000",
    "代表人姓名": "王_峯",
    "公司所在地": "臺北市中山區南京東路2段96號8樓",
    "登記機關": "臺北市政府",
    "核准設立日期": {
        "year": 1982,
        "month": 8,
        "day": 20
    },
    "最後核准變更日期": {
        "year": 2024,
        "month": 3,
        "day": 13
    },
    "所營事業資料": [
        [
            "",
            "各種生產事業之轉投資"
        ],
        [
            "",
            "證券投資公司銀行保險公司貿易公司文化事業等之轉投資"
        ],
        [
            "",
            "對興建商業大樓及國民住宅事業之轉投資"
        ]
    ],
    "董監事名單": [
        {
            "序號": "0001",
            "職稱": "董事長",
            "姓名": "王_峯",
            "所代表法人": "",
            "出資額": "83,000"
        },
        {
            "序號": "0002",
            "職稱": "董事",
            "姓名": "王_誠",
            "所代表法人": "",
            "出資額": "269,000"
        },
        {
            "序號": "0003",
            "職稱": "董事",
            "姓名": "王_萱",
            "所代表法人": "",
            "出資額": "593,000"
        },
        {
            "序號": "0004",
            "職稱": "監察人",
            "姓名": "王_麟",
            "所代表法人": "",
            "出資額": "766,000"
        }
    ],
    "經理人名單": [],
    "章程所訂外文公司名稱": "",
    "複數表決權特別股": "無",
    "對於特定事項具否決權特別股": "無",
    "每股金額(元)": "10",
    "已發行股份總數(股)": "7,600,000"
}