{
    "id": "07736110",
    "公司狀況": "解散",
    "公司名稱": "尚欣企業有限公司",
    "資本總額(元)": "3,000,000",
    "代表人姓名": "",
    "公司所在地": "臺北市大同區民族西路１６９巷２５號",
    "登記機關": "臺北市政府",
    "核准設立日期": {
        "year": 1980,
        "month": 10,
        "day": 10
    },
    "最後核准變更日期": {
        "year": 2005,
        "month": 7,
        "day": 14
    },
    "所營事業資料": [
        [
            "",
            "各種馬達電扇、電子五金、電機五金、家庭五金、建築五金、電器五金"
        ],
        [
            "",
            "　等加工製造業務"
        ],
        [
            "",
            "木器家具製造買賣業務"
        ],
        [
            "",
            "有關前項商品及其原料買賣、報價、投標、代銷進出口業務"
        ],
        [
            "",
            "就進出口業務之有關同業間對外保證"
        ],
        [
            "",
            "前各項有關業務之經營及投資"
        ]
    ],
    "董監事名單": [],
    "經理人名單": [],
    "舊營業項目資料": "http:\/\/gcis.nat.gov.tw..\/cmpy\/cmpyOriginalBusiItemAction.do?method=detail&banNo=07736110",
    "公司狀況日期": {
        "year": 2007,
        "month": 4,
        "day": 25
    },
    "公司狀況文號": "府建商字 第09683940500號"
}