{
    "id": "81153194",
    "公司狀況": "核准設立",
    "公司名稱": "運統企業有限公司",
    "資本總額(元)": "1,200,000",
    "代表人姓名": "徐_琪",
    "公司所在地": "高雄市苓雅區漢昌街84巷8號",
    "登記機關": "高雄市政府經濟發展局",
    "核准設立日期": {
        "year": 1979,
        "month": 6,
        "day": 8
    },
    "最後核准變更日期": {
        "year": 1989,
        "month": 1,
        "day": 28
    },
    "所營事業資料": [
        [
            "",
            "１﹒五金電料批發零售買賣"
        ],
        [
            "",
            "２﹒電動工具切削工具建築材料批發買賣"
        ],
        [
            "",
            "３﹒汽車百貨裝潢材料買賣"
        ],
        [
            "",
            "４﹒前項有關進出口業務經營及投資"
        ]
    ],
    "董監事名單": [
        {
            "序號": "0001",
            "職稱": "執行業務股東",
            "姓名": "徐_琪",
            "所代表法人": "",
            "出資額": "600,000"
        }
    ],
    "經理人名單": []
}