{
    "id": "83418761",
    "公司狀況": "撤銷",
    "公司名稱": "遠通企業股份有限公司",
    "資本總額(元)": "0",
    "實收資本額(元)": "0",
    "代表人姓名": "",
    "公司所在地": "高雄市前金區仁德街239號",
    "登記機關": "高雄市政府經濟發展局",
    "核准設立日期": {
        "year": 1981,
        "month": 3,
        "day": 6
    },
    "最後核准變更日期": {
        "year": 1992,
        "month": 5,
        "day": 28
    },
    "所營事業資料": [
        [
            "",
            "１﹒食品查菜畜產品（包括獸肉類）買賣"
        ],
        [
            "",
            "２﹒大理石加工及加工品買賣"
        ],
        [
            "",
            "３﹒手工藝品農產品（特許業務除外）等加工買賣"
        ],
        [
            "",
            "４﹒機械五金之買賣"
        ],
        [
            "",
            "５﹒木材製品加工及內外銷"
        ],
        [
            "",
            "６﹒化工原料之買賣及內外銷"
        ],
        [
            "",
            "７﹒布疋化學纖維等各種紡織品之製造加工及買賣業務"
        ],
        [
            "",
            "８﹒度量衡器及計量器等之進出口及買賣"
        ],
        [
            "",
            "９﹒一般進出口貿易業務"
        ],
        [
            "",
            "１０﹒就有關關進出口業務得外保證"
        ],
        [
            "",
            "１０﹒一，前各項有關業務之經營及投資"
        ]
    ],
    "董監事名單": [
        {
            "序號": "0004",
            "職稱": "監察人",
            "姓名": "林_發",
            "所代表法人": "",
            "出資額": "500"
        }
    ],
    "經理人名單": [],
    "舊營業項目資料": "http:\/\/gcis.nat.gov.tw..\/cmpy\/cmpyOriginalBusiItemAction.do?method=detail&banNo=83418761",
    "公司狀況日期": {
        "year": 1992,
        "month": 5,
        "day": 28
    },
    "公司狀況文號": "建二公字 第63911號"
}