{
    "id": "84117601",
    "公司狀況": "解散",
    "公司名稱": "歐港貿易有限公司",
    "資本總額(元)": "1,000,000",
    "代表人姓名": "",
    "公司所在地": "臺北市松山區南京東路４段７５號７樓之４",
    "登記機關": "臺北市政府",
    "核准設立日期": {
        "year": 1993,
        "month": 1,
        "day": 6
    },
    "最後核准變更日期": {
        "year": 1993,
        "month": 11,
        "day": 23
    },
    "所營事業資料": [
        [
            "",
            "各種針織、紡織布疋之織造加工及買賣業務。"
        ],
        [
            "",
            "塑膠鞋、皮鞋、休閒鞋、運動鞋及各種運動器材之買賣業務。"
        ],
        [
            "",
            "一般進出口貿易業務（期貨除外）（許可業務除外）。"
        ],
        [
            "",
            "代理前各項有關國內外廠商產品投標報價業務。"
        ]
    ],
    "董監事名單": [],
    "經理人名單": [],
    "公司狀況日期": {
        "year": 1993,
        "month": 11,
        "day": 23
    },
    "公司狀況文號": "建一字 第800801號"
}