{
    "id": "84403436",
    "公司狀況": "廢止",
    "公司名稱": "富地贏有限公司",
    "資本總額(元)": "3,000,000",
    "代表人姓名": "",
    "公司所在地": "臺中市南區西川里光明6巷146弄5號",
    "登記機關": "臺中市政府",
    "核准設立日期": {
        "year": 1993,
        "month": 6,
        "day": 17
    },
    "最後核准變更日期": {
        "year": 1994,
        "month": 4,
        "day": 12
    },
    "所營事業資料": [
        [
            "",
            "１﹒各種建築材料、五金建材買賣業務。"
        ],
        [
            "",
            "２﹒前項有關產品之進出口業務。"
        ],
        [
            "",
            "３﹒鋼筋加工、捆紮業務。"
        ],
        [
            "",
            "４﹒油漆粉刷工程業務。"
        ]
    ],
    "董監事名單": [],
    "經理人名單": [],
    "舊營業項目資料": "http:\/\/gcis.nat.gov.tw..\/cmpy\/cmpyOriginalBusiItemAction.do?method=detail&banNo=84403436",
    "公司狀況日期": {
        "year": 2008,
        "month": 4,
        "day": 29
    },
    "公司狀況文號": "經授中字 第0973481485號"
}