{
    "id": "84542177",
    "公司狀況": "解散",
    "公司名稱": "長虹廣告有限公司",
    "資本總額(元)": "1,000,000",
    "代表人姓名": "",
    "公司所在地": "臺中市北區漢口路四段三五號九樓",
    "登記機關": "臺中市政府",
    "核准設立日期": {
        "year": 1993,
        "month": 8,
        "day": 30
    },
    "最後核准變更日期": {
        "year": 1996,
        "month": 9,
        "day": 14
    },
    "所營事業資料": [
        [
            "",
            "１﹒工商廣告設計之業務。（許可業務除外）"
        ],
        [
            "",
            "２﹒房屋租售之介紹。"
        ],
        [
            "",
            "３﹒室內裝潢設計及建築材料買賣業務。（營造業除外）"
        ],
        [
            "",
            "４﹒前項有關產品之經銷、報價及投標。"
        ]
    ],
    "董監事名單": [],
    "經理人名單": [],
    "舊營業項目資料": "http:\/\/gcis.nat.gov.tw..\/cmpy\/cmpyOriginalBusiItemAction.do?method=detail&banNo=84542177",
    "公司狀況日期": {
        "year": 1996,
        "month": 9,
        "day": 14
    },
    "公司狀況文號": "建三壬字 第085231874號"
}