{
    "id": "84558450",
    "公司狀況": "解散",
    "公司名稱": "懷恩起重工程有限公司",
    "資本總額(元)": "2,000,000",
    "代表人姓名": "",
    "公司所在地": "新北市板橋區中正路一八三巷一七之二號三樓  ",
    "登記機關": "新北市政府",
    "核准設立日期": {
        "year": 1993,
        "month": 9,
        "day": 17
    },
    "最後核准變更日期": {
        "year": 2016,
        "month": 4,
        "day": 11
    },
    "所營事業資料": [
        [
            "",
            "１﹒一般起重工程承攬（營造業除外）。"
        ],
        [
            "",
            "２﹒土木機械（挖土機打樁機電動機起重機捲揚機吊車發動機）買賣及出租業務。"
        ],
        [
            "",
            "３﹒前項有關機械配件零件等買賣。"
        ]
    ],
    "董監事名單": [],
    "經理人名單": [],
    "舊營業項目資料": "https:\/\/gcis.nat.gov.tw..\/cmpy\/cmpyOriginalBusiItemAction.do?method=detail&banNo=84558450",
    "公司狀況日期": {
        "year": 2018,
        "month": 3,
        "day": 20
    },
    "公司狀況文號": "新北府經司字 第1078016496號"
}