{
    "id": "85780169",
    "公司狀況": "解散",
    "公司名稱": "鴻鈞國際企業有限公司",
    "資本總額(元)": "49,000,000",
    "代表人姓名": "",
    "公司所在地": "新北市中和區中山路二段四一九之一號",
    "登記機關": "新北市政府",
    "核准設立日期": {
        "year": 1977,
        "month": 9,
        "day": 7
    },
    "最後核准變更日期": {
        "year": 1996,
        "month": 9,
        "day": 3
    },
    "所營事業資料": [
        [
            "",
            "１﹒一般進出口業務"
        ],
        [
            "",
            "２﹒鋼琺瑯、模具、刺繡品之製造加工及買賣業務。"
        ],
        [
            "",
            "３﹒手工藝品、玉石、木彫刻、藝術圖、棉紗帶、尼龍帶、繩索買賣外銷。"
        ],
        [
            "",
            "４﹒前各項有關事業之經營及投資。"
        ]
    ],
    "董監事名單": [],
    "經理人名單": [
        {
            "序號": "0006",
            "姓名": "馬_林",
            "到職日期": null
        }
    ],
    "舊營業項目資料": "http:\/\/gcis.nat.gov.tw..\/cmpy\/cmpyOriginalBusiItemAction.do?method=detail&banNo=85780169",
    "公司狀況日期": {
        "year": 1996,
        "month": 9,
        "day": 3
    },
    "公司狀況文號": "建三甲字 第085218565號"
}