{
    "id": "86297706",
    "公司狀況": "核准設立",
    "公司名稱": "瑋迪股份有限公司",
    "資本總額(元)": "2,000,000",
    "實收資本額(元)": "2,000,000",
    "代表人姓名": "周_圳",
    "公司所在地": "臺北市松山區八德路4段300號2樓",
    "登記機關": "臺北市政府",
    "核准設立日期": {
        "year": 1991,
        "month": 10,
        "day": 19
    },
    "最後核准變更日期": null,
    "所營事業資料": [
        [
            "",
            "０１電腦軟體設計業務"
        ],
        [
            "",
            "０２有關影像處理系統、監視系統之規劃設計及安裝業務"
        ],
        [
            "",
            "０３自動化系統之規劃設計及安裝業務"
        ],
        [
            "",
            "０４保全、防盜系統之規劃設計及安裝業務"
        ],
        [
            "",
            "０５前各項有關業務之代理經銷報價投標業務"
        ],
        [
            "",
            "０６前各項有關業務之經營及轉投資"
        ]
    ],
    "董監事名單": [
        {
            "序號": "0000",
            "職稱": "董事長",
            "姓名": "周_圳",
            "所代表法人": "",
            "出資額": "0"
        },
        {
            "序號": "0000",
            "職稱": "監察人",
            "姓名": "郭_昌",
            "所代表法人": "",
            "出資額": "0"
        },
        {
            "序號": "0000",
            "職稱": "董事",
            "姓名": "林_強",
            "所代表法人": "",
            "出資額": "0"
        },
        {
            "序號": "0000",
            "職稱": "董事",
            "姓名": "簡_仁",
            "所代表法人": "",
            "出資額": "0"
        }
    ],
    "經理人名單": []
}