{
    "id": "86810079",
    "公司狀況": "核准設立",
    "公司名稱": "松聯水電工程有限公司",
    "資本總額(元)": "6,000,000",
    "代表人姓名": "方_松",
    "公司所在地": "宜蘭縣頭城鎮頂埔路二段193巷13號1樓",
    "登記機關": "經濟部中部辦公室",
    "核准設立日期": {
        "year": 1992,
        "month": 7,
        "day": 30
    },
    "最後核准變更日期": {
        "year": 2015,
        "month": 9,
        "day": 9
    },
    "所營事業資料": [
        [
            "F213010",
            "電器零售業。"
        ],
        [
            "E501011",
            "自來水管承裝商。"
        ],
        [
            "E601011",
            "電器承裝業。"
        ],
        [
            "F206040",
            "水電材料零售業。"
        ],
        [
            "F219010",
            "電子材料零售業。"
        ],
        [
            "F401010",
            "國際貿易業。"
        ]
    ],
    "董監事名單": [
        {
            "序號": "0001",
            "職稱": "董事",
            "姓名": "方_松",
            "所代表法人": "",
            "出資額": "6,000,000"
        }
    ],
    "經理人名單": [],
    "舊營業項目資料": "http:\/\/gcis.nat.gov.tw..\/cmpy\/cmpyOriginalBusiItemAction.do?method=detail&banNo=86810079"
}