{
    "id": "88405300",
    "公司狀況": "解散",
    "公司名稱": "德昌工業股份有限公司",
    "資本總額(元)": "22,000,000",
    "實收資本額(元)": "22,000,000",
    "代表人姓名": "",
    "公司所在地": "高雄市岡山區台上里大新街六六號",
    "登記機關": "高雄市政府經濟發展局",
    "核准設立日期": {
        "year": 1967,
        "month": 7,
        "day": 26
    },
    "最後核准變更日期": {
        "year": 2002,
        "month": 6,
        "day": 26
    },
    "所營事業資料": [
        [
            "",
            "１﹒黃豆油、黃豆粉、黃豆片、黃豆餅、花生油、花生餅、米糠油、米糠粕、菜籽油"
        ],
        [
            "",
            "　、菜籽粕、紅花子油、紅花籽　柏、椰子油、椰子粕、棉子油、棉子粕、亞芝蔴"
        ],
        [
            "",
            "　粕、亞芝蔴油、黑豆油、黑豆餅、烏蔴油、烏蔴餅、蔴粕、　桐油、桐粕及各"
        ],
        [
            "",
            "　種單元飼料、混合飼料、豬油、牛油、營養素等之製造加工及買賣。"
        ],
        [
            "",
            "２﹒前項各種原料及玉米、樹薯、簽粉、樹薯薟粉、甘薯薟粉、甘薯簽粉種子什谷糧"
        ],
        [
            "",
            "　食魚粉、小麥、大麥、麥麩、肥料、脫脂牛奶、魚精粉、紅豆等之進出口採購外"
        ],
        [
            "",
            "　銷批發零售及經紀業。"
        ],
        [
            "",
            "３﹒有關上列之倉庫業及代客加工。"
        ],
        [
            "",
            "４﹒自用劑餘廠房出租業務。"
        ],
        [
            "",
            "５﹒本公司為向政府機關標購原料得為經營同類業務之公司　或工廠向政府機關或金"
        ],
        [
            "",
            "　融機以公司名義承擔保證人。"
        ],
        [
            "F401010",
            "國際貿易業。"
        ]
    ],
    "董監事名單": [
        {
            "序號": "0004",
            "職稱": "監察人",
            "姓名": "林_固",
            "所代表法人": "",
            "出資額": "3,544"
        }
    ],
    "經理人名單": [
        {
            "序號": "0005",
            "姓名": "林_吉",
            "到職日期": {
                "year": 1979,
                "month": 2,
                "day": 10
            }
        }
    ],
    "舊營業項目資料": "http:\/\/gcis.nat.gov.tw..\/cmpy\/cmpyOriginalBusiItemAction.do?method=detail&banNo=88405300",
    "公司狀況日期": {
        "year": 2006,
        "month": 6,
        "day": 5
    },
    "公司狀況文號": "經授中字 第0953227499號"
}