{
    "id": "89231644",
    "公司名稱": "豪情企業有限公司",
    "資本總額(元)": "3,000,000",
    "代表人姓名": "陳_堂",
    "公司所在地": "臺中市西區三民西路17號11樓之2",
    "登記機關": "臺中市政府",
    "核准設立日期": {
        "year": 1994,
        "month": 8,
        "day": 6
    },
    "最後核准變更日期": {
        "year": 2024,
        "month": 8,
        "day": 1
    },
    "所營事業資料": [
        [
            "",
            "１﹒免洗尿片、衛生棉、化粧棉百貨買賣業務。"
        ],
        [
            "",
            "２﹒有關前項產品之進出口業務及代理國內外廠商經銷報價及投標業務。"
        ]
    ],
    "董監事名單": [
        {
            "序號": "0001",
            "職稱": "董事",
            "姓名": "陳_堂",
            "所代表法人": "",
            "出資額": "1,800,000"
        }
    ],
    "經理人名單": [],
    "章程所訂外文公司名稱": "",
    "登記現況": "核准設立"
}