{
    "id": "89571116",
    "公司狀況": "解散",
    "公司名稱": "群貫有限公司",
    "資本總額(元)": "5,000,000",
    "代表人姓名": "",
    "公司所在地": "臺中市北屯區更生巷二一二號二樓",
    "登記機關": "臺中市政府",
    "核准設立日期": {
        "year": 1995,
        "month": 6,
        "day": 29
    },
    "最後核准變更日期": {
        "year": 2005,
        "month": 9,
        "day": 27
    },
    "所營事業資料": [
        [
            "",
            "１﹒磁磚、砂石、水泥及建築材料之加工買賣業務。"
        ],
        [
            "",
            "２﹒前項產品之進出口貿易業務。"
        ],
        [
            "",
            "３﹒代理國內外廠商前各項產品之投資報價及經銷業務。"
        ],
        [
            "F111030",
            "磚、瓦、石建材批發業。"
        ],
        [
            "F111040",
            "磁磚、貼面石材批發業。"
        ],
        [
            "E801010",
            "室內裝潢業。"
        ]
    ],
    "董監事名單": [],
    "經理人名單": [],
    "舊營業項目資料": "http:\/\/gcis.nat.gov.tw..\/cmpy\/cmpyOriginalBusiItemAction.do?method=detail&banNo=89571116",
    "公司狀況日期": {
        "year": 2006,
        "month": 2,
        "day": 20
    },
    "公司狀況文號": "經授中字 第0953172156號"
}