{
    "id": "52614330",
    "公司狀況": "核准設立",
    "公司名稱": "精鍛機械股份有限公司",
    "資本總額(元)": "290,000,000",
    "實收資本額(元)": "290,000,000",
    "代表人姓名": "陳_仲",
    "公司所在地": "臺中市南屯區文山里精科一路11號",
    "登記機關": "臺中市政府",
    "核准設立日期": {
        "year": 1981,
        "month": 1,
        "day": 26
    },
    "最後核准變更日期": {
        "year": 2023,
        "month": 12,
        "day": 4
    },
    "所營事業資料": [
        [
            "",
            "１﹒沖床農機等機械及零件之製造修配及買賣。"
        ],
        [
            "",
            "２﹒模具製造加工買賣。"
        ],
        [
            "",
            "３﹒有關進出口貿易業務。"
        ]
    ],
    "董監事名單": [
        {
            "序號": "0001",
            "職稱": "董事長",
            "姓名": "陳_仲",
            "所代表法人": [
                "83585839",
                "利威投顧有限公司"
            ],
            "出資額": "49,300"
        },
        {
            "序號": "0002",
            "職稱": "董事",
            "姓名": "陳_亨",
            "所代表法人": [
                "83418592",
                "康納得有限公司"
            ],
            "出資額": "49,300"
        },
        {
            "序號": "0003",
            "職稱": "董事",
            "姓名": "林_場",
            "所代表法人": "",
            "出資額": "31,900"
        },
        {
            "序號": "0004",
            "職稱": "監察人",
            "姓名": "林_菁",
            "所代表法人": "",
            "出資額": "34,800"
        }
    ],
    "經理人名單": [],
    "章程所訂外文公司名稱": "JING DUANN MACHINERY INDUSTRIAL CO., LTD.",
    "複數表決權特別股": "無",
    "對於特定事項具否決權特別股": "無",
    "每股金額(元)": "1,000",
    "已發行股份總數(股)": "290,000"
}