{
    "id": "54573721",
    "公司狀況": "解散",
    "公司名稱": "明行有限公司",
    "資本總額(元)": "200,000",
    "代表人姓名": "",
    "公司所在地": "臺南市東區崇明里崇明路996號1樓  ",
    "登記機關": "臺南市政府",
    "核准設立日期": {
        "year": 2014,
        "month": 12,
        "day": 23
    },
    "最後核准變更日期": {
        "year": 2016,
        "month": 5,
        "day": 6
    },
    "所營事業資料": [
        [
            "F201010",
            "農產品零售業"
        ],
        [
            "F203010",
            "食品什貨、飲料零售業"
        ],
        [
            "F208040",
            "化粧品零售業"
        ],
        [
            "F501060",
            "餐館業"
        ],
        [
            "F206040",
            "水器材料零售業"
        ],
        [
            "F399990",
            "其他綜合零售業"
        ],
        [
            "ZZ99999",
            "除許可業務外，得經營法令非禁止或限制之業務"
        ]
    ],
    "董監事名單": [],
    "經理人名單": [],
    "公司狀況日期": {
        "year": 2019,
        "month": 3,
        "day": 19
    },
    "公司狀況文號": "府經工商字 第1080029665號"
}