{
    "id": "22357123",
    "公司狀況": "核准設立",
    "公司名稱": "功強有限公司",
    "資本總額(元)": "8,000,000",
    "代表人姓名": "吳_翰",
    "公司所在地": "臺北市中山區南京東路2段66號4樓之1",
    "登記機關": "臺北市政府",
    "核准設立日期": {
        "year": 1987,
        "month": 1,
        "day": 26
    },
    "最後核准變更日期": {
        "year": 2015,
        "month": 11,
        "day": 19
    },
    "所營事業資料": [
        [
            "",
            "一般進出口貿易業務︹許可業務除外︺"
        ],
        [
            "",
            "各種紙尿褲嬰幼兒食品奶粉餅乾罐頭糖果酵母顆粒及錠等食品之加工製"
        ],
        [
            "",
            "　造分裝買賣及進出口貿易業務"
        ],
        [
            "",
            "各種化工原料︹有毒性及管制品除外︺化粧品︹藥性除外︺之買賣及進"
        ],
        [
            "",
            "　出口貿易業務"
        ],
        [
            "",
            "各種醫療儀器科學儀器之買賣及進出口貿易業務"
        ],
        [
            "",
            "各種西藥之批發零售買賣等進出口貿易業務"
        ],
        [
            "",
            "各種食品、飲料及雜貨之買賣業務"
        ],
        [
            "",
            "代理前各項國內外廠商有關產品之投標報價及經銷業務︹期貨除外︺"
        ]
    ],
    "董監事名單": [
        {
            "序號": "0001",
            "職稱": "董事",
            "姓名": "吳_翰",
            "所代表法人": "",
            "出資額": "1,600,000"
        }
    ],
    "經理人名單": [],
    "舊營業項目資料": "http:\/\/gcis.nat.gov.tw..\/cmpy\/cmpyOriginalBusiItemAction.do?method=detail&banNo=22357123"
}