{
    "id": "22530833",
    "公司狀況": "解散",
    "公司名稱": "嘉高視聽企業有限公司",
    "資本總額(元)": "3,000,000",
    "代表人姓名": "",
    "公司所在地": "高雄市前鎮區台鋁12巷7號3樓",
    "登記機關": "高雄市政府經濟發展局",
    "核准設立日期": {
        "year": 1987,
        "month": 6,
        "day": 18
    },
    "最後核准變更日期": {
        "year": 1996,
        "month": 6,
        "day": 13
    },
    "所營事業資料": [
        [
            "",
            "一各種視聽器材︹投影機、幻灯機、攝影機、監視機、錄放影機︺、事務機器之代"
        ],
        [
            "",
            "理經銷買賣業務及各種視聽有關工程承包、施工、設計．"
        ],
        [
            "",
            "二科學理化儀器︹度量衡儀器除外︺、樂器之代理經銷買賣業務．"
        ],
        [
            "",
            "三代理有關前各項業務之國內外廠商產品買賣經銷報價業務．"
        ],
        [
            "",
            "四有關前各項事業之國內外經營及投資．"
        ]
    ],
    "董監事名單": [],
    "經理人名單": [],
    "舊營業項目資料": "http:\/\/gcis.nat.gov.tw..\/cmpy\/cmpyOriginalBusiItemAction.do?method=detail&banNo=22530833",
    "公司狀況日期": {
        "year": 1996,
        "month": 6,
        "day": 13
    },
    "公司狀況文號": "建二公字 第09560000號"
}