{
    "id": "22653573",
    "公司狀況": "核准設立",
    "公司名稱": "美日國際股份有限公司",
    "資本總額(元)": "18,000,000",
    "實收資本額(元)": "18,000,000",
    "代表人姓名": "王_朗",
    "公司所在地": "新北市新莊區新北大道3段5號16樓之8",
    "登記機關": "新北市政府",
    "核准設立日期": {
        "year": 1987,
        "month": 10,
        "day": 22
    },
    "最後核准變更日期": {
        "year": 2022,
        "month": 7,
        "day": 5
    },
    "所營事業資料": [
        [
            "",
            "一般進出口貿易業務︹許可業務除外︺"
        ],
        [
            "",
            "有關食品飲料之委外加工生產"
        ],
        [
            "",
            "飼料及飼料添加物之進出口及買賣業務"
        ],
        [
            "",
            "代理國內外廠商產品報價投標及經銷業務"
        ],
        [
            "",
            "樹脂原料之買賣業務"
        ],
        [
            "",
            "保鮮防黴抗菌劑之買賣業務"
        ],
        [
            "",
            "雜糧之進出口及買賣批發業務"
        ],
        [
            "",
            "食用油脂之進出口及買賣批發業務"
        ],
        [
            "F201030",
            "水產品零售業"
        ],
        [
            "F101050",
            "生鮮魚批發業"
        ],
        [
            "F102010",
            "冷凍食品批發業。"
        ],
        [
            "F203010",
            "食品飲料零售業"
        ],
        [
            "F401010",
            "國際貿易業"
        ]
    ],
    "董監事名單": [
        {
            "序號": "0001",
            "職稱": "董事長",
            "姓名": "王_朗",
            "所代表法人": [
                "12483071",
                "昌津股份有限公司"
            ],
            "出資額": "1,000,000"
        },
        {
            "序號": "0002",
            "職稱": "監察人",
            "姓名": "王_華",
            "所代表法人": "",
            "出資額": "0"
        }
    ],
    "經理人名單": [],
    "停業日期(起)": {
        "year": 2022,
        "month": 5,
        "day": 15
    },
    "停業日期(迄)": {
        "year": 2023,
        "month": 5,
        "day": 14
    },
    "停業核准(備)機關": "財政資訊中心轉入(轉入日期：111\/04\/24)",
    "章程所訂外文公司名稱": "",
    "複數表決權特別股": "無",
    "對於特定事項具否決權特別股": "無",
    "每股金額(元)": "10",
    "已發行股份總數(股)": "1,800,000"
}