{
    "id": "22910073",
    "公司狀況": "核准設立",
    "公司名稱": "建文陶藝有限公司",
    "資本總額(元)": "1,000,000",
    "代表人姓名": "馮_良",
    "公司所在地": "新北市鶯歌區文化路324巷1之3號  ",
    "登記機關": "新北市政府",
    "核准設立日期": {
        "year": 1988,
        "month": 4,
        "day": 29
    },
    "最後核准變更日期": {
        "year": 2018,
        "month": 5,
        "day": 23
    },
    "所營事業資料": [
        [
            "",
            "１﹒各種藝術陶瓷電花"
        ],
        [
            "",
            "２﹒各種藝術陶瓷製造加工買賣"
        ],
        [
            "",
            "３﹒有關前各項之進出口貿易業務"
        ]
    ],
    "董監事名單": [
        {
            "序號": "0001",
            "職稱": "董事",
            "姓名": "馮_良",
            "所代表法人": "",
            "出資額": "1,000,000"
        }
    ],
    "經理人名單": []
}