{
    "id": "23333395",
    "公司狀況": "撤銷",
    "公司名稱": "浩明企業有限公司",
    "資本總額(元)": "5,000,000",
    "代表人姓名": "",
    "公司所在地": "高雄市三民區汾陽路37號",
    "登記機關": "高雄市政府經濟發展局",
    "核准設立日期": {
        "year": 1989,
        "month": 6,
        "day": 10
    },
    "最後核准變更日期": {
        "year": 1992,
        "month": 5,
        "day": 25
    },
    "所營事業資料": [
        [
            "",
            "一鋁銅鋅錫暪□之買賣．"
        ],
        [
            "",
            "二鑄造材料、耐火材料、鑄造機械之代理經銷及買賣．"
        ],
        [
            "",
            "三輸配電線路器材、電纜配件之設計買賣．"
        ],
        [
            "",
            "四什貨買賣及大小五金、食品罐頭、食品機械等加工裝配製造買賣業務．"
        ],
        [
            "",
            "五有關前項業務之經營及轉投資並代理進出口貿易業務．"
        ],
        [
            "",
            "六代理國內外有關廠商報價經銷投標業務．"
        ]
    ],
    "董監事名單": [],
    "經理人名單": [],
    "舊營業項目資料": "http:\/\/gcis.nat.gov.tw..\/cmpy\/cmpyOriginalBusiItemAction.do?method=detail&banNo=23333395",
    "公司狀況日期": {
        "year": 1992,
        "month": 5,
        "day": 25
    },
    "公司狀況文號": "建二公字 第69303號"
}