{
    "id": "23382894",
    "公司狀況": "撤銷",
    "公司名稱": "裕年國際貿易股份有限公司",
    "資本總額(元)": "2,600,000",
    "實收資本額(元)": "2,600,000",
    "代表人姓名": "",
    "公司所在地": "新北市板橋區富山路二○號二樓",
    "登記機關": "新北市政府",
    "核准設立日期": {
        "year": 1989,
        "month": 7,
        "day": 3
    },
    "最後核准變更日期": {
        "year": 2000,
        "month": 4,
        "day": 25
    },
    "所營事業資料": [
        [
            "",
            "１﹒一般進出口貿易業務（期貨除外）。"
        ],
        [
            "",
            "２﹒電子器材及其零件家電產品（電冰箱、電視機、洗衣機、電風扇、音響　、錄放"
        ],
        [
            "",
            "　影機、收錄音機、烤麵包機、微波爐、烘乾機、烘碗機、電磁爐　、冷氣機等）"
        ],
        [
            "",
            "　之買賣業務。"
        ],
        [
            "",
            "３﹒農業機械測試儀器（度量衡除外）汽機車零件及保養用品買賣業務。"
        ],
        [
            "",
            "４﹒肥料買賣業務。"
        ],
        [
            "",
            "５﹒電腦及其週邊設備買賣業務。"
        ],
        [
            "",
            "６﹒冷凍食品及罐頭等買賣業務。"
        ],
        [
            "",
            "７﹒代理前項有關國內外廠商產品之投標報價及經銷業務。"
        ],
        [
            "",
            "８﹒前項有關業務之經營及轉投資。"
        ]
    ],
    "董監事名單": [
        {
            "序號": "0004",
            "職稱": "監察人",
            "姓名": "吳_秀",
            "所代表法人": "",
            "出資額": "0"
        }
    ],
    "經理人名單": [],
    "舊營業項目資料": "http:\/\/gcis.nat.gov.tw..\/cmpy\/cmpyOriginalBusiItemAction.do?method=detail&banNo=23382894",
    "公司狀況日期": {
        "year": 2000,
        "month": 4,
        "day": 25
    },
    "公司狀況文號": "經89中字 第089550106號"
}