{
    "id": "23936537",
    "公司狀況": "撤銷",
    "公司名稱": "峻源工程有限公司",
    "資本總額(元)": "1,000,000",
    "代表人姓名": "",
    "公司所在地": "新北市中和區永和路六六巷三○弄一四號一樓",
    "登記機關": "新北市政府",
    "核准設立日期": {
        "year": 1990,
        "month": 11,
        "day": 15
    },
    "最後核准變更日期": {
        "year": 1994,
        "month": 2,
        "day": 28
    },
    "所營事業資料": [
        [
            "",
            "１﹒防■工程之承包業務。"
        ],
        [
            "",
            "２﹒油漆工程之承包及塗料之買賣業務（營造業除外在客戶處施工）。"
        ],
        [
            "",
            "３﹒室內裝潢宮殿彩畫及隔音吸音等設備按裝工程之設計承包業務（營造業除外）。"
        ],
        [
            "",
            "４﹒一般防水防漏防潮濕防腐防蝕防熱等業務設計及材料加以施工補漏（營造業除外"
        ],
        [
            "",
            "　在客戶現場作業）。"
        ],
        [
            "",
            "５﹒各種建築材料之買賣業務。"
        ],
        [
            "",
            "６﹒前各項有關產品及原料之進出口貿易業務。"
        ],
        [
            "",
            "７﹒代理國內外前各項有關產品報價投標及經銷業務。"
        ],
        [
            "",
            "８﹒前各項有關業務之經營及轉投資。"
        ]
    ],
    "董監事名單": [],
    "經理人名單": [],
    "舊營業項目資料": "http:\/\/gcis.nat.gov.tw..\/cmpy\/cmpyOriginalBusiItemAction.do?method=detail&banNo=23936537",
    "公司狀況日期": {
        "year": 1994,
        "month": 2,
        "day": 28
    },
    "公司狀況文號": "建三管字 第083273170號"
}