{
    "id": "29529918",
    "公司狀況": "核准設立",
    "公司名稱": "土城精機廠有限公司",
    "資本總額(元)": "5,000,000",
    "代表人姓名": "林_進",
    "公司所在地": "臺北市士林區葫蘆街30巷41弄2號1樓",
    "登記機關": "臺北市政府",
    "核准設立日期": {
        "year": 1979,
        "month": 4,
        "day": 30
    },
    "最後核准變更日期": {
        "year": 2005,
        "month": 2,
        "day": 14
    },
    "所營事業資料": [
        [
            "",
            "針車及零件製造販賣業務"
        ],
        [
            "",
            "機械及零件製造販賣業務"
        ],
        [
            "",
            "五金機械買賣業務"
        ],
        [
            "",
            "有關前項業務之進出口貿易及就該項業務為同業間對外之保證"
        ],
        [
            "",
            "其他有關事業之投資經營業務"
        ]
    ],
    "董監事名單": [
        {
            "序號": "0001",
            "職稱": "董事",
            "姓名": "林_進",
            "所代表法人": "",
            "出資額": "5,000,000"
        }
    ],
    "經理人名單": []
}